simspy/__init__.py
simspy/fcsimspy.py
simspy-1.2.0.dist-info/LICENSE.txt
simspy-1.2.0.dist-info/METADATA
simspy-1.2.0.dist-info/WHEEL
simspy-1.2.0.dist-info/top_level.txt
simspy-1.2.0.dist-info/RECORD
