Metadata-Version: 2.1
Name: simspy
Version: 1.2.0
Summary: SIMSPY is an 8-function package that can only solve single machine scheduling problems
Home-page: 
Author: Milla and Kewalin
Author-email: millah211@gmail.com, kewalin-16@hotmail.com
Classifier: Programming Language :: Python :: 3
Classifier: License :: OSI Approved :: MIT License
Classifier: Operating System :: OS Independent
Requires-Python: >=3.7
License-File: LICENSE.txt
Requires-Dist: ttkbootstrap
